BeginnersbookJavaShiliChuyiFix1/README.md
BeginnersbookJavaShiliChuyiFix1/__init__.py
BeginnersbookJavaShiliChuyiFix1/__main__.py
BeginnersbookJavaShiliChuyiFix1/file.epub
BeginnersbookJavaShiliChuyiFix1/index.html
BeginnersbookJavaShiliChuyiFix1/css/__init__.py
BeginnersbookJavaShiliChuyiFix1/css/annotations.css
BeginnersbookJavaShiliChuyiFix1/css/main.css
BeginnersbookJavaShiliChuyiFix1/css/normalize.css
BeginnersbookJavaShiliChuyiFix1/css/popup.css
BeginnersbookJavaShiliChuyiFix1/font/__init__.py
BeginnersbookJavaShiliChuyiFix1/font/fontello.eot
BeginnersbookJavaShiliChuyiFix1/font/fontello.svg
BeginnersbookJavaShiliChuyiFix1/font/fontello.ttf
BeginnersbookJavaShiliChuyiFix1/font/fontello.woff
BeginnersbookJavaShiliChuyiFix1/img/__init__.py
BeginnersbookJavaShiliChuyiFix1/img/annotator-glyph-sprite.png
BeginnersbookJavaShiliChuyiFix1/img/annotator-icon-sprite.png
BeginnersbookJavaShiliChuyiFix1/img/apple-touch-icon.png
BeginnersbookJavaShiliChuyiFix1/img/cancelfullscreen.png
BeginnersbookJavaShiliChuyiFix1/img/close.png
BeginnersbookJavaShiliChuyiFix1/img/fullscreen.png
BeginnersbookJavaShiliChuyiFix1/img/loader.gif
BeginnersbookJavaShiliChuyiFix1/img/menu-icon.png
BeginnersbookJavaShiliChuyiFix1/img/save.png
BeginnersbookJavaShiliChuyiFix1/img/saved.png
BeginnersbookJavaShiliChuyiFix1/img/settings-s.png
BeginnersbookJavaShiliChuyiFix1/img/settings.png
BeginnersbookJavaShiliChuyiFix1/img/star.png
BeginnersbookJavaShiliChuyiFix1/js/__init__.py
BeginnersbookJavaShiliChuyiFix1/js/epub.js
BeginnersbookJavaShiliChuyiFix1/js/epub.min.js
BeginnersbookJavaShiliChuyiFix1/js/epub.min.map
BeginnersbookJavaShiliChuyiFix1/js/hooks.min.js
BeginnersbookJavaShiliChuyiFix1/js/hooks.min.map
BeginnersbookJavaShiliChuyiFix1/js/reader.js
BeginnersbookJavaShiliChuyiFix1/js/reader.js.map
BeginnersbookJavaShiliChuyiFix1/js/reader.min.js
BeginnersbookJavaShiliChuyiFix1/js/reader.min.map
BeginnersbookJavaShiliChuyiFix1/js/hooks/__init__.py
beginnersbook_java_shili_chuyi_fix1-2025.3.23.0.dist-info/METADATA
beginnersbook_java_shili_chuyi_fix1-2025.3.23.0.dist-info/WHEEL
beginnersbook_java_shili_chuyi_fix1-2025.3.23.0.dist-info/entry_points.txt
beginnersbook_java_shili_chuyi_fix1-2025.3.23.0.dist-info/top_level.txt
beginnersbook_java_shili_chuyi_fix1-2025.3.23.0.dist-info/RECORD
